{
  "app:toggle-right-sidebar": [
    {
      "modifiers": [
        "Alt",
        "Mod"
      ],
      "key": "R"
    }
  ],
  "app:toggle-left-sidebar": [
    {
      "modifiers": [
        "Alt",
        "Mod"
      ],
      "key": "L"
    }
  ],
  "workspace:split-vertical": [
    {
      "modifiers": [
        "Alt",
        "Mod"
      ],
      "key": "\\"
    }
  ],
  "workspace:split-horizontal": [
    {
      "modifiers": [
        "Alt",
        "Mod"
      ],
      "key": "H"
    }
  ],
  "nldates-obsidian:nlp-time": [
    {
      "modifiers": [
        "Mod",
        "Shift"
      ],
      "key": ";"
    }
  ],
  "todoist-sync-plugin:todoist-add-task": [
    {
      "modifiers": [
        "Alt",
        "Shift"
      ],
      "key": "A"
    }
  ],
  "editor:fold-all": [
    {
      "modifiers": [
        "Alt",
        "Mod"
      ],
      "key": "C"
    }
  ],
  "editor:unfold-all": [
    {
      "modifiers": [
        "Alt",
        "Mod"
      ],
      "key": "E"
    }
  ],
  "obsidian-mind-map:app:markmap-preview": [
    {
      "modifiers": [
        "Alt",
        "Mod"
      ],
      "key": "M"
    }
  ],
  "outline:open": [
    {
      "modifiers": [
        "Alt",
        "Mod"
      ],
      "key": "U"
    }
  ],
  "workspace:toggle-pin": [
    {
      "modifiers": [
        "Alt",
        "Mod"
      ],
      "key": "P"
    }
  ],
  "editor:set-heading-1": [
    {
      "modifiers": [
        "Alt",
        "Mod"
      ],
      "key": "1"
    }
  ],
  "editor:set-heading-2": [
    {
      "modifiers": [
        "Alt",
        "Mod"
      ],
      "key": "2"
    }
  ],
  "editor:set-heading-3": [
    {
      "modifiers": [
        "Ctrl",
        "Alt"
      ],
      "key": "3"
    }
  ],
  "editor:set-heading-4": [
    {
      "modifiers": [
        "Ctrl",
        "Alt"
      ],
      "key": "4"
    }
  ],
  "editor:set-heading-5": [
    {
      "modifiers": [
        "Ctrl",
        "Alt"
      ],
      "key": "5"
    }
  ],
  "editor:set-heading-6": [
    {
      "modifiers": [
        "Ctrl",
        "Alt"
      ],
      "key": "6"
    }
  ],
  "app:delete-file": [
    {
      "modifiers": [
        "Mod"
      ],
      "key": "Backspace"
    }
  ],
  "editor:toggle-source": [
    {
      "modifiers": [
        "Alt",
        "Mod"
      ],
      "key": "Y"
    }
  ],
  "graph:open-local": [
    {
      "modifiers": [
        "Alt",
        "Mod"
      ],
      "key": "G"
    }
  ]
}